[
  {
    "id": 1,
    "album": {
      "can_be_archived": false,
      "on_spotify": false,
      "album_name": "Test",
      "genre_name": "testgenre"
    }
  },
  {
    "id": 2,
    "album": {
      "can_be_archived": false,
      "on_spotify": false,
      "album_name": "sdsd",
      "genre_name": "gfdg"
    }
  },
  {
    "id": 3,
    "album": {
      "can_be_archived": false,
      "on_spotify": false,
      "album_name": "dd",
      "genre_name": "f"
    }
  },
  {
    "id": 4,
    "album": {
      "can_be_archived": false,
      "on_spotify": false,
      "album_name": "ff",
      "genre_name": "g"
    }
  }
]